ai_api_py/__init__.py
ai_api_py-0.1.0.dist-info/METADATA
ai_api_py-0.1.0.dist-info/WHEEL
ai_api_py-0.1.0.dist-info/RECORD
