Metadata-Version: 2.1
Name: ai-api-py
Version: 0.1.0
Summary: API-based AI model serving
Author: Sebastiao
Author-email: sgafonso.dev@pm.me
Requires-Python: >=3.10,<4.0
Classifier: Programming Language :: Python :: 3
Classifier: Programming Language :: Python :: 3.10
Classifier: Programming Language :: Python :: 3.11
Classifier: Programming Language :: Python :: 3.12
